pyezbeq/__init__.py
pyezbeq/consts.py
pyezbeq/errors.py
pyezbeq/ezbeq.py
pyezbeq/models.py
pyezbeq/py.typed
pyezbeq/search.py
pyezbeq/utils.py
tests/__init__.py
tests/conftest.py
tests/consts.py
tests/test_codecs.py
tests/test_ezbeq.py
tests/test_functional.py
pyezbeq-0.0.8.dist-info/LICENSE
pyezbeq-0.0.8.dist-info/METADATA
pyezbeq-0.0.8.dist-info/WHEEL
pyezbeq-0.0.8.dist-info/top_level.txt
pyezbeq-0.0.8.dist-info/RECORD
