Metadata-Version: 2.1
Name: pyezbeq
Version: 0.0.8
Summary: A package to control ezbeq
Home-page: https://github.com/iloveicedgreentea/pyezbeq
Author: iloveicedgreentea2
Classifier: Programming Language :: Python :: 3.12
Classifier: License :: OSI Approved :: GNU General Public License v3 (GPLv3)
Classifier: Operating System :: OS Independent
License-File: LICENSE
